[
  {
    "context": "Workspace",
    "bindings": {
      "ctrl-shift-enter": "terminal_panel::ToggleFocus",
      "ctrl-shift-t": "workspace::NewTerminal",
      "ctrl-9": "project_panel::ToggleFocus"
    }
  },
  {
    "context": "Editor && vim_mode == normal",
    "bindings": {
      "ctrl-shift-enter": "terminal_panel::ToggleFocus",
      "ctrl-shift-t": "workspace::NewTerminal",
      "space b": "workspace::ToggleLeftDock",
      "space p": "workspace::ToggleRightDock",
      "space enter": "workspace::ToggleBottomDock"
    }
  },
  {
    "context": "vim_mode == visual",
    "bindings": {
      "p": ["workspace::SendKeystrokes", "p g v y"]
    }
  },
  {
    "context": "Editor && vim_mode == visual || vim_mode == normal",
    "bindings": {
      "space /": "editor::ToggleComments"
    }
  }
]
